mcp_reddit/__init__.py
mcp_reddit/__main__.py
mcp_reddit/scraper.py
mcp_reddit/server.py
mcp_reddit-0.3.0.dist-info/METADATA
mcp_reddit-0.3.0.dist-info/WHEEL
mcp_reddit-0.3.0.dist-info/entry_points.txt
mcp_reddit-0.3.0.dist-info/licenses/LICENSE
mcp_reddit-0.3.0.dist-info/RECORD
