Metadata-Version: 2.4
Name: mcp-reddit
Version: 0.3.0
Summary: MCP server for scraping Reddit - no API keys required
Project-URL: Homepage, https://github.com/namanxajmera/mcp-reddit
Project-URL: Repository, https://github.com/namanxajmera/mcp-reddit
Project-URL: Issues, https://github.com/namanxajmera/mcp-reddit/issues
Author: Naman
License-Expression: MIT
License-File: LICENSE
Keywords: anthropic,claude,mcp,reddit,scraper
Classifier: Development Status :: 4 - Beta
Classifier: Intended Audience :: Developers
Classifier: License :: OSI Approved :: MIT License
Classifier: Programming Language :: Python :: 3
Classifier: Programming Language :: Python :: 3.10
Classifier: Programming Language :: Python :: 3.11
Classifier: Programming Language :: Python :: 3.12
Requires-Python: >=3.10
Requires-Dist: aiofiles>=23.0.0
Requires-Dist: aiohttp>=3.9.0
Requires-Dist: mcp>=1.0.0
Requires-Dist: pandas>=2.0.0
Requires-Dist: starlette>=0.38.0
Requires-Dist: uvicorn>=0.30.0
Provides-Extra: dev
Requires-Dist: pytest-asyncio>=0.21.0; extra == 'dev'
Requires-Dist: pytest>=7.0.0; extra == 'dev'
